folk/__init__.py
folk/_version.py
folk/cfg.py
folk/evaluate.py
folk/exceptions.py
folk/metricsdb.py
folk/model.py
folk/pipe.py
folk-0.0.9.dist-info/METADATA
folk-0.0.9.dist-info/RECORD
folk-0.0.9.dist-info/WHEEL
folk-0.0.9.dist-info/top_level.txt
tests/__init__.py
tests/shared.py
tests/test_evaluate.py
tests/test_model.py
tests/test_pipe.py
