Metadata-Version: 2.1
Name: folk
Version: 0.0.9
Summary: Folksy experiment management for Machine Learning.
Home-page: https://github.com/shaypal5/folk
Author: Shay Palachy
Author-email: shay.palachy@gmail.com
License: UNKNOWN
Platform: UNKNOWN
Classifier: Development Status :: 4 - Beta
Classifier: License :: OSI Approved :: MIT License
Classifier: Programming Language :: Python
Classifier: Programming Language :: Python :: 3.5
Classifier: Programming Language :: Python :: 3.6
Classifier: Topic :: Software Development :: Libraries
Classifier: Topic :: Software Development :: Libraries :: Python Modules
Classifier: Intended Audience :: Developers
Provides-Extra: test
Requires-Dist: numpy
Requires-Dist: scipy
Requires-Dist: scikit-learn
Requires-Dist: birch (>=0.0.8)
Requires-Dist: decore
Requires-Dist: strct
Requires-Dist: pdutil
Requires-Dist: pymongo
Provides-Extra: test
Requires-Dist: pytest; extra == 'test'
Requires-Dist: coverage; extra == 'test'
Requires-Dist: pytest-cov; extra == 'test'
Requires-Dist: pandas; extra == 'test'
Requires-Dist: pdpipe; extra == 'test'
Requires-Dist: skutil; extra == 'test'
Requires-Dist: collective.checkdocs; extra == 'test'
Requires-Dist: pygments; extra == 'test'
Requires-Dist: numpy; extra == 'test'
Requires-Dist: scipy; extra == 'test'
Requires-Dist: scikit-learn; extra == 'test'
Requires-Dist: birch (>=0.0.8); extra == 'test'
Requires-Dist: decore; extra == 'test'
Requires-Dist: strct; extra == 'test'
Requires-Dist: pdutil; extra == 'test'
Requires-Dist: pymongo; extra == 'test'
